audio_recorder/__init__.py
audio_recorder/main.py
audio_recorder_AGN-0.1.0.dist-info/METADATA
audio_recorder_AGN-0.1.0.dist-info/WHEEL
audio_recorder_AGN-0.1.0.dist-info/entry_points.txt
audio_recorder_AGN-0.1.0.dist-info/top_level.txt
audio_recorder_AGN-0.1.0.dist-info/RECORD
