Metadata-Version: 2.1
Name: audio-recorder-AGN
Version: 0.1.0
Summary: A simple audio recording library.
Home-page: https://github.com/yourusername/audio_recorder
Author: Your Name
Classifier: Programming Language :: Python :: 3
Classifier: License :: OSI Approved :: MIT License
Classifier: Operating System :: OS Independent
Requires-Dist: sounddevice
Requires-Dist: numpy
